fluentxy/__init__.py
fluentxy/tests/__init__.py
fluentxy/tests/test_fluentxy.py
fluentxy/tests/data/axial-velocity-mesh-1.csv
fluentxy/tests/data/axial-velocity-mesh-1.xy
fluentxy/tests/data/axial-velocity-mesh-2.csv
fluentxy/tests/data/axial-velocity-mesh-2.xy
fluentxy-0.1.0.dist-info/LICENSE
fluentxy-0.1.0.dist-info/WHEEL
fluentxy-0.1.0.dist-info/METADATA
fluentxy-0.1.0.dist-info/RECORD
