Metadata-Version: 2.1
Name: fluentxy
Version: 0.1.0
Summary: An interface to produce Pandas DataFrames from Fluent XY output files.
Home-page: https://github.com/bryanwweber/fluentxy
License: UNKNOWN
Author: Bryan W. Weber
Author-email: bryan.w.weber@gmail.com
Requires-Python: ~=3.6
Classifier: License :: OSI Approved :: BSD License
Classifier: Programming Language :: Python :: 3
Classifier: Development Status :: 3 - Alpha
Classifier: Programming Language :: Python :: 3 :: Only
Requires-Dist: parse
Requires-Dist: pandas
Requires-Dist: numpy
Provides-Extra: .none
